anncorra/__init__.py
anncorra/anncorra.py
anncorra/pos_tags_data.json
anncorra-0.0.4.dist-info/LICENSE.txt
anncorra-0.0.4.dist-info/METADATA
anncorra-0.0.4.dist-info/WHEEL
anncorra-0.0.4.dist-info/top_level.txt
anncorra-0.0.4.dist-info/RECORD
