Metadata-Version: 2.1
Name: anncorra
Version: 0.0.4
Summary: Anncorra is a python package for giving meaning to POS (Part of Speech) tags.
Home-page: https://github.com/kuldip-barot/anncorra/anncorra
Author: Kuldeep Barot
License: Apache License 2.0
Platform: UNKNOWN
Classifier: Development Status :: 3 - Alpha
Classifier: License :: OSI Approved :: Apache Software License
Classifier: Programming Language :: Python
Classifier: Programming Language :: Python :: 3.5
Classifier: Programming Language :: Python :: 3.6
Classifier: Topic :: Software Development :: Libraries
Classifier: Topic :: Software Development :: Libraries :: Python Modules
Classifier: Intended Audience :: Developers
Requires-Python: >=3.5
